{
  "main": {
    "id": "87a92759a1db6dd6",
    "type": "split",
    "children": [
      {
        "id": "bf431b21593ab98f",
        "type": "tabs",
        "children": [
          {
            "id": "d55dd104c966a8bc",
            "type": "leaf",
            "state": {
              "type": "thino_view",
              "state": {},
              "icon": "Memos",
              "title": "Thino"
            }
          },
          {
            "id": "17a4ad7c8f2141d5",
            "type": "leaf",
            "state": {
              "type": "markdown",
              "state": {
                "file": "Daily/2025-05-17.md",
                "mode": "source",
                "source": false
              },
              "icon": "lucide-file",
              "title": "2025-05-17"
            }
          }
        ]
      }
    ],
    "direction": "vertical"
  },
  "left": {
    "id": "adfc7253791b9f94",
    "type": "split",
    "children": [
      {
        "id": "7343c84c8e990154",
        "type": "tabs",
        "children": [
          {
            "id": "b38cd64456c453f0",
            "type": "leaf",
            "state": {
              "type": "file-explorer",
              "state": {
                "sortOrder": "alphabetical",
                "autoReveal": false
              },
              "icon": "lucide-folder-closed",
              "title": "ファイルエクスプローラ"
            }
          },
          {
            "id": "1e0a247fb1cfa24f",
            "type": "leaf",
            "state": {
              "type": "search",
              "state": {
                "query": "",
                "matchingCase": false,
                "explainSearch": false,
                "collapseAll": false,
                "extraContext": false,
                "sortOrder": "alphabetical"
              },
              "icon": "lucide-search",
              "title": "検索"
            }
          },
          {
            "id": "2820f7caecfb09e6",
            "type": "leaf",
            "state": {
              "type": "bookmarks",
              "state": {},
              "icon": "lucide-bookmark",
              "title": "ブックマーク"
            }
          },
          {
            "id": "43e9f204e52eaf3b",
            "type": "leaf",
            "state": {
              "type": "calendar",
              "state": {},
              "icon": "lucide-file",
              "title": "アクティブでなくなったプラグイン"
            }
          }
        ]
      }
    ],
    "direction": "horizontal",
    "width": 200
  },
  "right": {
    "id": "a76cc0c282dc424c",
    "type": "split",
    "children": [
      {
        "id": "e16966375ce6697a",
        "type": "tabs",
        "children": [
          {
            "id": "156d3cc9be1786f1",
            "type": "leaf",
            "state": {
              "type": "backlink",
              "state": {
                "file": "Daily/2025-05-15.md",
                "collapseAll": false,
                "extraContext": false,
                "sortOrder": "alphabetical",
                "showSearch": false,
                "searchQuery": "",
                "backlinkCollapsed": false,
                "unlinkedCollapsed": true
              },
              "icon": "links-coming-in",
              "title": "2025-05-15へのバックリンク"
            }
          },
          {
            "id": "d0d6bfedf09c4abf",
            "type": "leaf",
            "state": {
              "type": "outgoing-link",
              "state": {
                "file": "Welcome.md",
                "linksCollapsed": false,
                "unlinkedCollapsed": true
              },
              "icon": "links-going-out",
              "title": "Welcomeからのアウトゴーイングリンク"
            }
          },
          {
            "id": "edcfba19d1a34df2",
            "type": "leaf",
            "state": {
              "type": "tag",
              "state": {
                "sortOrder": "frequency",
                "useHierarchy": true,
                "showSearch": false,
                "searchQuery": ""
              },
              "icon": "lucide-tags",
              "title": "タグ"
            }
          },
          {
            "id": "7b6fcf179b8ee415",
            "type": "leaf",
            "state": {
              "type": "outline",
              "state": {
                "followCursor": false,
                "showSearch": false,
                "searchQuery": ""
              },
              "icon": "lucide-list",
              "title": "アウトライン"
            }
          },
          {
            "id": "59347387790305ca",
            "type": "leaf",
            "state": {
              "type": "git-view",
              "state": {},
              "icon": "git-pull-request",
              "title": "Source Control"
            }
          }
        ],
        "currentTab": 4
      }
    ],
    "direction": "horizontal",
    "width": 200
  },
  "left-ribbon": {
    "hiddenItems": {
      "switcher:クイックスイッチャーを開く": false,
      "graph:グラフビューを開く": false,
      "canvas:新規キャンバスを作成": false,
      "daily-notes:今日のデイリーノートを開く": false,
      "templates:テンプレートを挿入": false,
      "command-palette:コマンドパレットを開く": false,
      "obsidian-git:Open Git source control": false,
      "line-notes-sync:Sync LINE messages": false,
      "obsidian-memos:Thino": false
    }
  },
  "active": "d55dd104c966a8bc",
  "lastOpenFiles": [
    "Daily/2025-05-17.md",
    "Zettelkasten/Zettelkastenの運用/Obsidian Git v2.33.0 設定メモ.md",
    "無題のファイル.canvas",
    "Daily/2025-05-15.md",
    "Daily/2025-05-16.md",
    "Zettelkasten/LiteratureNote/新宿三丁目店｜松尾ジンギスカン公式サイト 北海道の札幌・滝川・千歳などに展開.md",
    "README.md",
    "Templates/README.md",
    "Welcome.md",
    "MEMO(Thino)",
    "無題のファイル.md",
    "Zettelkasten/LiteratureNote/Obsidian Web Clipper × AI でWebページを自動要約＆ストックしてみた  DevelopersIO.md",
    "LINE/2025-05-16-561200066975760555.md",
    "LINE/2025-05-16-561189338449969307.md",
    "Zettelkasten/LiteratureNote/単なるメモから知的資産へ：Obsidian in Cursorで構築する知的生産システム｜松濤Vimmer.md",
    "LINE/2025-05-16-561233421607895297.md",
    "LINE/2025-05-16-561197361683497064.md",
    "Zettelkasten/LiteratureNote/「Obsidian」と「Cursor」を使って、noteの記事をどんどこ書く｜akane.md",
    "Clippings/単なるメモから知的資産へ：Obsidian in Cursorで構築する知的生産システム｜松濤Vimmer.md",
    "Clippings",
    "Zettelkasten/Zettelkastenの運用",
    "Zettelkasten/PermanentNote",
    "Zettelkasten/LiteratureNote",
    "Zettelkasten/IndexNote",
    "Zettelkasten/FleetingNote",
    "Zettelkasten",
    "LINE",
    "Zettels/README.md",
    "Zettels/無題のファイル.md",
    "Templates/Zettel.md",
    "関連するZettel2.md",
    "readme.md",
    "関連Zettel名.md",
    "Logs/Reading/README.md",
    "Templates/Slide.md",
    "Templates"
  ]
}